__init__.py
setup.py
tkengine.py
TkEngine.egg-info/PKG-INFO
TkEngine.egg-info/SOURCES.txt
TkEngine.egg-info/dependency_links.txt
TkEngine.egg-info/requires.txt
TkEngine.egg-info/top_level.txt