Metadata-Version: 1.1
Name: TkEngine
Version: 1.0.4
Summary: A GUI and Game engine with pyglet.
Home-page: https://github.com/tlebrize/TkEngine
Author: tlebrize
Author-email: tlebrize@student.42.fr
License: BEER-WARE LICENSE (https://en.wikipedia.org/wiki/Beerware)
Keywords: engine pyglet python python3 gui
Platform: UNKNOWN
Classifier: Development Status :: 3 - Alpha
Classifier: Programming Language :: Python :: 3.6
